HISTORY.rst
LICENSE
MANIFEST.in
NOTICE
README.rst
requirements.txt
setup.cfg
setup.py
test_requests.py
yieldfrom/__init__.py
yieldfrom.requests.egg-info/PKG-INFO
yieldfrom.requests.egg-info/SOURCES.txt
yieldfrom.requests.egg-info/dependency_links.txt
yieldfrom.requests.egg-info/namespace_packages.txt
yieldfrom.requests.egg-info/not-zip-safe
yieldfrom.requests.egg-info/requires.txt
yieldfrom.requests.egg-info/top_level.txt
yieldfrom/requests/__init__.py
yieldfrom/requests/adapters.py
yieldfrom/requests/api.py
yieldfrom/requests/auth.py
yieldfrom/requests/cacert.pem
yieldfrom/requests/certs.py
yieldfrom/requests/compat.py
yieldfrom/requests/cookies.py
yieldfrom/requests/exceptions.py
yieldfrom/requests/hooks.py
yieldfrom/requests/models.py
yieldfrom/requests/sessions.py
yieldfrom/requests/status_codes.py
yieldfrom/requests/structures.py
yieldfrom/requests/utils.py