Metadata-Version: 1.1
Name: yieldfrom.requests
Version: 0.1.3
Summary: asyncio port of Requests: "Python HTTP for Humans".
Home-page: https://github.com/rdbhost/yieldfromrequests
Author: David Keeney
Author-email: dkeeney@rdbhost.com
License: Apache 2.0
Platform: UNKNOWN
Classifier: b'Intended Audience :: Developers'
Classifier: b'Natural Language :: English'
Classifier: b'License :: OSI Approved :: Apache Software License'
Classifier: b'Programming Language :: Python'
Classifier: b'Programming Language :: Python :: 3.3'
Classifier: b'Programming Language :: Python :: 3.4'
